Metadata-Version: 1.1
Name: validatorpkg
Version: 0.0.1
Summary: Validator Package for user info
Home-page: UNKNOWN
Author: Andrei Capi
Author-email: lizardcoder6@gmail.com
License: MIT
Keywords: calculator
Platform: UNKNOWN
Classifier: Development Status :: 5 - Production/Stable
Classifier: Intended Audience :: Education
Classifier: Operating System :: Microsoft :: Windows :: Windows 10
Classifier: License :: OSI Approved :: MIT License
Classifier: Programming Language :: Python :: 3
